interview_questions/__init__.py
interview_questions/__main__.py
interview_questions/cli.py
interview_questions/commands.py
interview_questions/database.py
interview_questions/defaults.py
interview_questions/menu.py
interview_questions/printer.py
interview_star_questions-1.6.0.dist-info/METADATA
interview_star_questions-1.6.0.dist-info/WHEEL
interview_star_questions-1.6.0.dist-info/entry_points.txt
interview_star_questions-1.6.0.dist-info/top_level.txt
interview_star_questions-1.6.0.dist-info/RECORD
